RPi/_GPIO.cpython-310-arm-linux-gnueabihf.so
RPi/__init__.py
RPi/GPIO/__init__.py
RPi.GPIO-0.7.1a4.dist-info/LICENCE.txt
RPi.GPIO-0.7.1a4.dist-info/METADATA
RPi.GPIO-0.7.1a4.dist-info/WHEEL
RPi.GPIO-0.7.1a4.dist-info/top_level.txt
RPi.GPIO-0.7.1a4.dist-info/RECORD
