Metadata-Version: 2.1
Name: RPi.GPIO
Version: 0.7.1a4
Summary: A module to control Raspberry Pi GPIO channels
Home-page: http://sourceforge.net/projects/raspberry-gpio-python/
Author: Ben Croston
Author-email: ben@croston.org
License: MIT
Keywords: Raspberry Pi GPIO
Platform: UNKNOWN
Classifier: Development Status :: 5 - Production/Stable
Classifier: Operating System :: POSIX :: Linux
Classifier: License :: OSI Approved :: MIT License
Classifier: Intended Audience :: Developers
Classifier: Programming Language :: Python :: 2.7
Classifier: Programming Language :: Python :: 3
Classifier: Topic :: Software Development
Classifier: Topic :: Home Automation
Classifier: Topic :: System :: Hardware
